risc_generator/__init__.py
risc_generator/version.py
risc_generator/content/__init__.py
risc_generator/content/config.py
risc_generator/content/en/__init__.py
risc_generator/content/en/bill.py
risc_generator/content/en/cancellation_of_policy.py
risc_generator/content/en/certificates.py
risc_generator/content/en/client_advantages.py
risc_generator/content/en/declaration.py
risc_generator/content/en/fpq_1.py
risc_generator/content/en/general_header.py
risc_generator/content/en/header.py
risc_generator/content/en/important_instructions.py
risc_generator/content/en/declaration_articles/__init__.py
risc_generator/content/en/declaration_articles/items.py
risc_generator/content/en/endorsements/__init__.py
risc_generator/content/en/endorsements/endorsement_header.py
risc_generator/content/en/endorsements/faq13.py
risc_generator/content/en/endorsements/faq16.py
risc_generator/content/en/endorsements/faq19.py
risc_generator/content/en/endorsements/faq2.py
risc_generator/content/en/endorsements/faq20.py
risc_generator/content/en/endorsements/faq20a.py
risc_generator/content/en/endorsements/faq23a.py
risc_generator/content/en/endorsements/faq25.py
risc_generator/content/en/endorsements/faq27.py
risc_generator/content/en/endorsements/faq27a.py
risc_generator/content/en/endorsements/faq28.py
risc_generator/content/en/endorsements/faq3.py
risc_generator/content/en/endorsements/faq30.py
risc_generator/content/en/endorsements/faq31.py
risc_generator/content/en/endorsements/faq32.py
risc_generator/content/en/endorsements/faq33.py
risc_generator/content/en/endorsements/faq34.py
risc_generator/content/en/endorsements/faq34ab.py
risc_generator/content/en/endorsements/faq37ab.py
risc_generator/content/en/endorsements/faq40.py
risc_generator/content/en/endorsements/faq41.py
risc_generator/content/en/endorsements/faq43.py
risc_generator/content/en/endorsements/faq5a.py
risc_generator/content/en/endorsements/faq8.py
risc_generator/content/en/endorsements/faq9.py
risc_generator-0.0.3.dist-info/LICENSE
risc_generator-0.0.3.dist-info/METADATA
risc_generator-0.0.3.dist-info/WHEEL
risc_generator-0.0.3.dist-info/top_level.txt
risc_generator-0.0.3.dist-info/RECORD
