Metadata-Version: 2.1
Name: risc-generator
Version: 0.0.3
Summary: RISC, an open-source Python package data generator. RISC generates look-alike automobile insurance contracts based on the Quebec regulatory insurance form in French and English.
Download-URL: https://github.com/GRAAL-Research/risc/archive/v0.0.3.zip
Author: David Beauchemin
Author-email: david.beauchemin.5@ulaval.ca
License: LGPLv3
Classifier: Development Status :: 3 - Alpha
Classifier: Intended Audience :: Developers
Classifier: Intended Audience :: Education
Classifier: Intended Audience :: Science/Research
Classifier: License :: OSI Approved :: GNU Lesser General Public License v3 (LGPLv3)
Classifier: Programming Language :: Python :: 3
Classifier: Programming Language :: Python :: 3.8
Classifier: Programming Language :: Python :: 3.9
Classifier: Programming Language :: Python :: 3.10
Classifier: Topic :: Software Development :: Libraries
Classifier: Topic :: Software Development :: Libraries :: Python Modules
Classifier: Topic :: Scientific/Engineering
Classifier: Topic :: Scientific/Engineering :: Artificial Intelligence
Requires-Python: >=3.8
License-File: LICENSE
